{
    "FindGoal": {
        "checkpoints": [
            {
                "steps": 499975,
                "file_path": "results\\TrainTest1\\FindGoal\\FindGoal-499975.onnx",
                "reward": 1.0,
                "creation_time": 1656239196.2134593,
                "auxillary_file_paths": [
                    "results\\TrainTest1\\FindGoal\\FindGoal-499975.pt"
                ]
            },
            {
                "steps": 500023,
                "file_path": "results\\TrainTest1\\FindGoal\\FindGoal-500023.onnx",
                "reward": 1.0,
                "creation_time": 1656239196.2742963,
                "auxillary_file_paths": [
                    "results\\TrainTest1\\FindGoal\\FindGoal-500023.pt"
                ]
            }
        ],
        "final_checkpoint": {
            "steps": 500023,
            "file_path": "results\\TrainTest1\\FindGoal.onnx",
            "reward": 1.0,
            "creation_time": 1656239196.2742963,
            "auxillary_file_paths": [
                "results\\TrainTest1\\FindGoal\\FindGoal-500023.pt"
            ]
        }
    },
    "metadata": {
        "stats_format_version": "0.3.0",
        "mlagents_version": "0.29.0",
        "torch_version": "1.7.0+cu110"
    }
}